resim/geometry/proto/oriented_box_pb2.py
resim/geometry/python/polygon_distance_python.so
resim/metrics/dice_coefficient.py
resim/metrics/fetch_all_pages.py
resim/metrics/fetch_job_metrics.py
resim/metrics/fetch_metrics_urls.py
resim/metrics/get_metrics_proto.py
resim/metrics/proto/metrics_pb2.py
resim/metrics/python/metrics.py
resim/metrics/python/metrics_utils.py
resim/metrics/python/metrics_writer.py
resim/metrics/python/unpack_metrics.py
resim/transforms/proto/frame_3_pb2.py
resim/transforms/proto/se3_pb2.py
resim/transforms/python/geodetic_python.so
resim/transforms/python/quaternion.so
resim/transforms/python/se3_python.so
resim/transforms/python/so3_python.so
resim/utils/proto/uuid_pb2.py
resim_metrics-0.0.0.dist-info/WHEEL
resim_metrics-0.0.0.dist-info/METADATA
resim_metrics-0.0.0.dist-info/RECORD
