Metadata-Version: 2.1
Name: resim_metrics
Author: ReSim Developers
Home-page: https://www.resim.ai/
License: Copyright 2025 ReSim, Inc.
Summary: ReSim Metrics Libraries.
Classifier: License :: OSI Approved :: MIT License
Requires-Dist: numpy>=1.25.2
Requires-Dist: pandas<3,>=1.5.3
Requires-Dist: plotly>=5.22.0
Requires-Dist: polling2>=0.5.0
Requires-Dist: requests>=2.31.0
Requires-Dist: httpx>=0.25.2
Version: 0.0.0
